MANIFEST.in
README.md
setup.py
version.txt
pyperlin/__init__.py
pyperlin/fractalperlin.py
pyperlin.egg-info/PKG-INFO
pyperlin.egg-info/SOURCES.txt
pyperlin.egg-info/dependency_links.txt
pyperlin.egg-info/top_level.txt
pyperlin/tests/__init__.py
pyperlin/tests/testfractalperlin.py