Metadata-Version: 2.1
Name: pyperlin
Version: 1.1.0
Summary: GPU accelerated Perlin noise
Home-page: https://github.com/duchesneaumathieu/pyperlin
Author: Mathieu Duchesneau
Author-email: duchesneau.mathieu@gmail.com
License: UNKNOWN
Platform: UNKNOWN
Classifier: Programming Language :: Python :: 3
Classifier: Intended Audience :: Science/Research
Classifier: License :: OSI Approved :: MIT License
Classifier: Operating System :: OS Independent
Requires-Python: >=3.6
